odoo8_addon_l10n_it_ipa-8.0.2.0.0.99.dev3-py2.7-nspkg.pth
odoo8_addon_l10n_it_ipa-8.0.2.0.0.99.dev3.dist-info/METADATA
odoo8_addon_l10n_it_ipa-8.0.2.0.0.99.dev3.dist-info/RECORD
odoo8_addon_l10n_it_ipa-8.0.2.0.0.99.dev3.dist-info/WHEEL
odoo8_addon_l10n_it_ipa-8.0.2.0.0.99.dev3.dist-info/namespace_packages.txt
odoo8_addon_l10n_it_ipa-8.0.2.0.0.99.dev3.dist-info/top_level.txt
odoo_addons/l10n_it_ipa/README.rst
odoo_addons/l10n_it_ipa/__init__.py
odoo_addons/l10n_it_ipa/__openerp__.py
odoo_addons/l10n_it_ipa/i18n/es.po
odoo_addons/l10n_it_ipa/i18n/it.po
odoo_addons/l10n_it_ipa/i18n/l10n_it_ipa.pot
odoo_addons/l10n_it_ipa/i18n/sl.po
odoo_addons/l10n_it_ipa/model/__init__.py
odoo_addons/l10n_it_ipa/model/partner.py
odoo_addons/l10n_it_ipa/static/description/icon.png
odoo_addons/l10n_it_ipa/view/partner_view.xml
